{
	"applicantInfo": {
		"fullName": "",
		"email": "user@example.com",
		"countryCode": "",
		"mobileNo": "",
		"applyOnbehalf": true
	},
	"generalInfo": {
		"prospectId": "",
		"_links": {
			"self": {
				"href": ""
			}
		},
		"cifId": 0,
		"customerType": "",
		"dsaId": "",
		"groupId": "",
		"groupName": "",
		"rmCode": "",
		"accountManagerId": "",
		"isPoliticallyExposed": "N"
	},
	"applicationInfo": {
		"viewId": "",
		"islamicBanking": true,
		"accountType": "RAKStarter",
		"rakValuePackage": "RAKvalue PLUS",
		"leadNumber": "",
		"riskScore": "",
		"srNumber": "",
		"channelId": "Bank to confirm on the LOVs",
		"channelType": "Mobile",
		"createdDate": "",
		"lastModifiedDate": "",
		"createdBy": "",
		"lastModifiedBy": "",
		"actionType": "Save",
		"saveType": "auto",
		"tncAgreed": false,
		"declaration": true
	},
	"accountInfo": [
		{
			"branchId": "LOVs will be fetched from datalist API",
			"accountType": "Segment of the user to be checked with Vartika, coz based upon that account scheme code wil vary",
			"accountSubType": "Segment of the user to be checked with Vartika, coz based upon that account scheme code wil vary",
			"accountNo": "",
			"accountCurrencies": [
				""
			],
			"accountCurrency": "AED",
			"accountPurpose": "Bank to confirm on the LOVs",
			"debitCardApplied": true,
			"chequeBookApplied": true,
			"eStatements": true,
			"mailStatements": false,
			"receiveInterest": true,
			"deliverByCourier": true
		}
	],
	"organizationInfo": {
		"screeningInfo": {
			"statusOverAll": "proceed",
			"screeningResults": [
				{
					"screeningType": "",
					"screeningStatus": "",
					"screeningFlag": "",
					"screeningNotes": "",
					"screeningReason": "",
					"reasonNotes": "",
					"reasonCode": "",
					"reasonStatus": ""
				}
			]
		},
		"branchCity": "LOVs to be confirmed by Bank",
		"branchID": "LOVs to be confirmed by Bank",
		"countryOfIncorporation": "AE",
		"companyName": "",
		"shortName": "",
		"dateOfIncorporation": "2019-10-09",
		"numberOfEmployees": 0,
		"licenseType": "Trade License",
		"licenseTypeOther": "",
		"licenseIssuingAuthority": "LOVs to be confirmed by Bank",
		"licenseNumber": "",
		"licenseIssueDate": "2019-10-09",
		"licenseExpiryDate": "2019-10-09",
		"vatRegistrationNumber": "",
		"addressInfo": [
			{
				"typeOfAddress": "Registered Address/Head office",
				"officeAddressDifferent": "No",
				"addressDetails": [
					{
						"addressFieldDesc": "Registered Address/Head office",
						"preferredAddress": "Yes",
						"addressLine1": "",
						"addressLine2": "",
						"addressLine3": "",
						"addressLine4": "",
						"poBox": "",
						"emirateCity": "",
						"country": "",
						"typeOfSpaceOccupied": {
							"spaceType": "Office",
							"others": ""
						}
					}
				]
			}
		],
		"contactDetails": {
			"primaryMobileNo": "",
			"primaryMobCountryCode": "",
			"primaryEmail": "user@example.com",
			"primaryPhoneNo": "",
			"primaryPhoneCountryCode": "",
			"fax": "",
			"faxCountryCode": "",
			"secondaryPhoneNo": "",
			"secondaryPhoneCountryCode": "",
			"secondaryMobileNo": "",
			"secondaryMobileCountryCode": "",
			"secondaryEmail": "user@example.com",
			"website": ""
		},
		"contactDetailsForTxnReconfirming": [
			{
				"primaryMobileNo": "",
				"primaryMobCountryCode": "",
				"primaryPhoneNo": "",
				"primaryPhoneCountryCode": ""
			}
		]
	},
	"orgKYCDetails": {
		"businessUnit": "PBD",
		"constitutionType": "Proprietorship",
		"companyCategory": "Charitable Trust",
		"annualFinTurnoverAmtInAED": "",
		"yearsInBusiness": 0,
		"topCustomers": [
			{
				"name": "",
				"country": "LOVs to be fetched from datalist API"
			}
		],
		"topSuppliers": [
			{
				"name": "",
				"country": "LOVs to be fetched from datalist API"
			}
		],
		"topOriginGoodsCountries": [
			"LOVs to be fetched from datalist API"
		],
		"industryMultiSelect": [
			{
				"industry": [
					"LOVs to be shared by Bank"
				],
				"subCategory": [
					"LOVs to be shared by Bank"
				]
			}
		],
		"anticipatedTransactionsDetails": {
			"totalMonthlyCashCreditsAED": {
				"amountInFigures": "",
				"inPercent": 0
			},
			"totalMonthlyNonCashCreditsAED": {
				"amountInFigures": "",
				"inPercent": 0
			},
			"totalMonthlyCreditsAED": "",
			"maxAmtSingleTxnCashAED": "",
			"maxAmtSingleTxnNonCashAED": ""
		},
		"otherBankingRelationshipsInfo": {
			"otherBankingRelationshipsExist": false,
			"otherBankDetails": [
				{
					"bankName": ""
				}
			]
		},
		"otherEntitiesInUAE": false,
		"entitiesInUAE": [
			{
				"companyName": "",
				"emirate": "LOVs to be fetched from data list API",
				"tradeLicenseNo": ""
			}
		],
		"otherEntitiesOutsideUAE": false,
		"entitiesOutsideUAE": [
			{
				"companyName": "",
				"country": "LOVs to be fetched from data list API"
			}
		],
		"isShareholderACompany": false
	},
	"signatoryInfo": [
		{
			"screeningInfo": {
				"statusOverAll": "proceed",
				"screeningResults": [
					{
						"screeningType": "",
						"screeningStatus": "",
						"screeningFlag": "",
						"screeningNotes": "",
						"screeningReason": "",
						"reasonNotes": "",
						"reasonCode": "",
						"reasonStatus": ""
					}
				]
			},
			"salutation": "Mr.",
			"signatoryId": "",
			"firstName": "",
			"middleName": "",
			"lastName": "",
			"shortName": "",
			"fullName": "",
			"gender": "Male",
			"maritalStatus": "Married",
			"maritalStatusOthers": "",
			"occupation": "",
			"mothersMaidenName": "",
			"numberOfDependants": 0,
			"highestEducationAttained": "",
			"employmentStatus": "",
			"kycVerified": false,
			"kycDetails": {
				"salutation": "Mr.",
				"shareholderPOASignatoryName": "",
				"isSignatory": false,
				"isShareholder": false,
				"shareHoldingPercentage": 0,
				"dateOfBirth": "2019-10-09",
				"nationality": "",
				"dualCitizenship": false,
				"dualCitizenshipCountry": [
					"LOVs to be fetched from datalist API"
				],
				"residenceCountry": "AE",
				"isUAEResident": false,
				"passportDetails": [
					{
						"passportNumber": "",
						"passportExpiryDate": "2019-10-09",
						"diplomatPassport": false
					}
				],
				"emirateIdDetails": {
					"eidNumber": "",
					"eidExpiryDt": "2019-10-09"
				},
				"selfGovtPosition": "Currently hold",
				"relativeGovtPosition": "Currently hold",
				"isPEP": false,
				"qualification": "Under Graduate",
				"experienceInYrs": "",
				"sourceOfWealth": {
					"wealthType": "Personal Savings",
					"others": ""
				}
			},
			"contactDetails": {
				"primaryMobileNo": "",
				"primaryMobCountryCode": "",
				"primaryEmail": "user@example.com",
				"primaryPhoneNo": "",
				"primaryPhoneCountryCode": "",
				"fax": "",
				"faxCountryCode": "",
				"secondaryPhoneNo": "",
				"secondaryPhoneCountryCode": "",
				"secondaryMobileNo": "",
				"secondaryMobileCountryCode": "",
				"secondaryEmail": "user@example.com",
				"website": ""
			},
			"employmentDetails": {
				"employmentType": "Salaried",
				"otherEmploymentType": "",
				"designation": "",
				"empNo": "",
				"department": "",
				"employerName": "",
				"occupation": "",
				"totalExperienceYrs": 0,
				"employmentStartDate": "2019-10-09"
			},
			"sameAsCompanyAddress": false,
			"addressInfo": [
				{
					"typeOfAddress": "Residence Address",
					"addressDetails": [
						{
							"addressFieldDesc": "Residence Address",
							"preferredAddress": "Yes",
							"addressLine1": "",
							"addressLine2": "",
							"addressLine3": "",
							"addressLine4": "",
							"poBox": "",
							"emirateCity": "",
							"country": ""
						}
					]
				}
			],
			"accountSigningInfo": {
				"accountSigningType": "Any of us",
				"accountSigningInstn": "",
				"authorityType": "SP - Sole Proprietor"
			},
			"debitCardInfo": {
				"issueDebitCard": true,
				"authSignatoryDetails": {
					"fullNameOnPassport": "",
					"nameOnDebitCard": ""
				}
			}
		}
	],
	"channelServicesInfo": {
		"mobileInstructions": false,
		"marketingSMS": false,
		"doNotDisturbHours": "",
		"weeklyBalanceNotification": "Sunday",
		"monthlyBalanceNotification": 0
	},
	"documents": {
		"companyDocuments": [
			{
				"documentType": "Passport",
				"signatoryId": "",
				"signatoryName": "",
				"documentTitle": "",
				"documentKey": "",
				"fileName": "",
				"filePath": "",
				"url": "",
				"fileData": "",
				"fileFormat": "application/pdf",
				"fileSize": 0,
				"fileDescription": "",
				"submittedBy": "",
				"submittedDt": "",
				"updatedBy": "",
				"updatedDt": "",
				"avsCheckDt": "",
				"avsCheck": false,
				"verified": false,
				"verifiedBy": "",
				"isEncrypted": false,
				"required": true,
				"encryptionDetails": "",
				"uploadStatus": "NotUploaded"
			}
		],
		"stakeholdersDocuments": {
			"index_stakeholderName": {
				"documents": [
					{
						"documentType": "",
						"signatoryId": "",
						"signatoryName": "",
						"documentTitle": "",
						"documentKey": "",
						"fileName": "",
						"filePath": "",
						"url": "",
						"fileData": "",
						"fileFormat": "",
						"fileSize": 0,
						"fileDescription": "",
						"submittedBy": "",
						"submittedDt": "",
						"updatedBy": "",
						"updatedDt": "",
						"avsCheckDt": "",
						"avsCheck": false,
						"verified": false,
						"verifiedBy": "",
						"isEncrypted": false,
						"required": true,
						"encryptionDetails": "",
						"uploadStatus": ""
					}
				]
			}
		}
	},
	"prospectStatusInfo": {
		"statusType": "",
		"statusCode": "",
		"statusFlag": "",
		"statusNotes": "",
		"statusReason": "",
		"statusOverAll": "",
		"reasonNotes": "",
		"reasonCode": "",
		"reasonStatus": ""
	},
	"freeFieldsInfo": {
		"freeField1": "",
		"freeField2": "",
		"freeField3": "",
		"freeField4": "",
		"freeField5": ""
	}
}